MANIFEST.in
README.rst
setup.py
versiontools_support.py
pastry/__init__.py
pastry/exceptions.py
pastry/pastry_client.py
pastry.egg-info/PKG-INFO
pastry.egg-info/SOURCES.txt
pastry.egg-info/dependency_links.txt
pastry.egg-info/not-zip-safe
pastry.egg-info/requires.txt
pastry.egg-info/top_level.txt
pastry/resources/__init__.py
pastry/resources/base.py
pastry/resources/cookbooks.py
pastry/resources/databags.py
pastry/resources/environments.py
pastry/resources/groups.py
pastry/resources/nodes.py
pastry/resources/pushy.py
pastry/resources/search.py
pastry/resources/users.py
pastry/utils/__init__.py
pastry/utils/auth.py
pastry/utils/pastry_rsa.py
tests/__init__.py
tests/test_exceptions.py
tests/test_pastry_client.py
tests/resources/__init__.py
tests/resources/test_base.py
tests/resources/test_cookbooks.py
tests/resources/test_databags.py
tests/resources/test_environments.py
tests/resources/test_groups.py
tests/resources/test_nodes.py
tests/resources/test_pushy.py
tests/resources/test_search.py
tests/resources/test_users.py
tests/utils/__init__.py
tests/utils/test_auth.py
tests/utils/test_pastry_rsa.py