Metadata-Version: 1.0
Name: pastry
Version: 0.1.31
Summary: A simple api wrapper for chef
Home-page: https://github.com/stephenbm/pastry
Author: Stephen Breyer-Menke
Author-email: steve.bm@gmail.com
License: MIT
Platform: UNKNOWN
